CHANGES.rst
README.rst
development.ini
setup.cfg
setup.py
kotti_tagcloud/__init__.py
kotti_tagcloud/fanstatic.py
kotti_tagcloud/populate.py
kotti_tagcloud/widget.py
kotti_tagcloud.egg-info/PKG-INFO
kotti_tagcloud.egg-info/SOURCES.txt
kotti_tagcloud.egg-info/dependency_links.txt
kotti_tagcloud.egg-info/entry_points.txt
kotti_tagcloud.egg-info/not-zip-safe
kotti_tagcloud.egg-info/requires.txt
kotti_tagcloud.egg-info/top_level.txt
kotti_tagcloud/locale/README
kotti_tagcloud/locale/kotti_tagcloud.pot
kotti_tagcloud/locale/de/LC_MESSAGES/kotti_tagcloud.mo
kotti_tagcloud/locale/de/LC_MESSAGES/kotti_tagcloud.po
kotti_tagcloud/locale/en/LC_MESSAGES/kotti_tagcloud.mo
kotti_tagcloud/locale/en/LC_MESSAGES/kotti_tagcloud.po
kotti_tagcloud/static/css/style.css
kotti_tagcloud/static/css/style.min.css
kotti_tagcloud/static/img/README
kotti_tagcloud/static/js/excanvas.js
kotti_tagcloud/static/js/excanvas.min.js
kotti_tagcloud/static/js/jquery.tagcanvas.js
kotti_tagcloud/static/js/jquery.tagcanvas.min.js
kotti_tagcloud/static/js/script.js
kotti_tagcloud/static/js/script.min.js
kotti_tagcloud/templates/tagcloud.pt
kotti_tagcloud/tests/conftest.py
kotti_tagcloud/tests/test_configure.py
local/CHANGES.rst
local/README.rst
local/development.ini
local/setup.cfg
local/setup.py
local/kotti_tagcloud/__init__.py
local/kotti_tagcloud/fanstatic.py
local/kotti_tagcloud/populate.py
local/kotti_tagcloud/widget.py
local/kotti_tagcloud/locale/README
local/kotti_tagcloud/locale/kotti_tagcloud.pot
local/kotti_tagcloud/locale/de/LC_MESSAGES/kotti_tagcloud.mo
local/kotti_tagcloud/locale/de/LC_MESSAGES/kotti_tagcloud.po
local/kotti_tagcloud/locale/en/LC_MESSAGES/kotti_tagcloud.mo
local/kotti_tagcloud/locale/en/LC_MESSAGES/kotti_tagcloud.po
local/kotti_tagcloud/static/css/style.css
local/kotti_tagcloud/static/css/style.min.css
local/kotti_tagcloud/static/img/README
local/kotti_tagcloud/static/js/excanvas.js
local/kotti_tagcloud/static/js/excanvas.min.js
local/kotti_tagcloud/static/js/jquery.tagcanvas.js
local/kotti_tagcloud/static/js/jquery.tagcanvas.min.js
local/kotti_tagcloud/static/js/script.js
local/kotti_tagcloud/static/js/script.min.js
local/kotti_tagcloud/templates/tagcloud.pt
local/kotti_tagcloud/tests/conftest.py
local/kotti_tagcloud/tests/test_configure.py